.gitignore
CHANGELOG.md
CONTRIBUTING.md
LICENSE.txt
Makefile
README.md
RELEASE.md
environment.yml
pyproject.toml
requirements-dev.txt
requirements.txt
runtime.txt
setup.cfg
setup.py
.github/workflows/test.yml
docs/flights_hist.png
notebooks/nycflights-dev.ipynb
notebooks/nycflights.ipynb
spark_plot/__init__.py
spark_plot/_generated_version.py
spark_plot/hist.py
spark_plot/mpl.py
spark_plot.egg-info/PKG-INFO
spark_plot.egg-info/SOURCES.txt
spark_plot.egg-info/dependency_links.txt
spark_plot.egg-info/not-zip-safe
spark_plot.egg-info/requires.txt
spark_plot.egg-info/top_level.txt
spark_plot/tests/__init__.py
spark_plot/tests/test_import.py